remlaversionutilpy/__init__.py
remlaversionutilpy/remlaversionutilpy.py
remlaversionutilpy-0.1.2.dist-info/LICENSE
remlaversionutilpy-0.1.2.dist-info/METADATA
remlaversionutilpy-0.1.2.dist-info/WHEEL
remlaversionutilpy-0.1.2.dist-info/RECORD
